gcwebsockets-9.1.1.dist-info/WHEEL
gcwebsockets-9.1.1.dist-info/METADATA
gcwebsockets-9.1.1.dist-info/LICENSE
gcwebsockets-9.1.1.dist-info/RECORD
gcwebsockets-9.1.1.dist-info/top_level.txt
websockets/datastructures.py
websockets/py.typed
websockets/connection.py
websockets/__init__.py
websockets/version.py
websockets/http.py
websockets/auth.py
websockets/exceptions.py
websockets/imports.py
websockets/server.py
websockets/typing.py
websockets/speedups.c
websockets/speedups.cpython-310-x86_64-linux-gnu.so
websockets/headers.py
websockets/uri.py
websockets/client.py
websockets/streams.py
websockets/__main__.py
websockets/http11.py
websockets/utils.py
websockets/frames.py
websockets/extensions/permessage_deflate.py
websockets/extensions/__init__.py
websockets/extensions/base.py
websockets/legacy/handshake.py
websockets/legacy/__init__.py
websockets/legacy/http.py
websockets/legacy/auth.py
websockets/legacy/compatibility.py
websockets/legacy/server.py
websockets/legacy/client.py
websockets/legacy/protocol.py
websockets/legacy/framing.py
