Metadata-Version: 2.1
Name: gcwebsockets
Version: 9.1.1
Summary: An implementation of the WebSocket Protocol (RFC 6455 & 7692)
Home-page: https://github.com/aaugustin/websockets
Author: Aymeric Augustin
Author-email: aymeric.augustin@m4x.org
License: BSD
Classifier: Development Status :: 5 - Production/Stable
Classifier: Environment :: Web Environment
Classifier: Intended Audience :: Developers
Classifier: License :: OSI Approved :: BSD License
Classifier: Operating System :: OS Independent
Classifier: Programming Language :: Python
Classifier: Programming Language :: Python :: 3
Classifier: Programming Language :: Python :: 3.6
Classifier: Programming Language :: Python :: 3.7
Classifier: Programming Language :: Python :: 3.8
Classifier: Programming Language :: Python :: 3.9
Requires-Python: >=3.6.1
License-File: LICENSE
